labreporthelper/__init__.py
labreporthelper/datafile.py
labreporthelper/dataset.py
labreporthelper/manage.py
labreporthelper/misc.py
labreporthelper/parse.py
labreporthelper/plot.py
labreporthelper/table.py
labreporthelper/bestfit/__init__.py
labreporthelper/bestfit/bestfit.py
labreporthelper/bestfit/curvefit.py
labreporthelper/bestfit/expfit.py
labreporthelper/bestfit/polyfit.py
labreporthelper-0.2.2.data/scripts/make-lab-report
labreporthelper-0.2.2.dist-info/DESCRIPTION.rst
labreporthelper-0.2.2.dist-info/METADATA
labreporthelper-0.2.2.dist-info/RECORD
labreporthelper-0.2.2.dist-info/WHEEL
labreporthelper-0.2.2.dist-info/metadata.json
labreporthelper-0.2.2.dist-info/pbr.json
labreporthelper-0.2.2.dist-info/top_level.txt
