Metadata-Version: 2.0
Name: labreporthelper
Version: 0.2.2
Summary: Collection of shortcut methods commonly used to generate plots and tables in lab reports
Home-page: https://github.com/calvinku96/labreporthelper
Author: Calvin
Author-email: calvinku96@gmail.com
License: MIT
Platform: UNKNOWN
Requires-Dist: importlib
Requires-Dist: matplotlib
Requires-Dist: numpy
Requires-Dist: scipy
